LICENSE
README.md
pyproject.toml
.github/workflows/python-publish.yml
docs/Makefile
docs/abbrev_long.bib
docs/conf.py
docs/conf_overrides.py
docs/conf_spec.py
docs/index.rst
docs/make.bat
docs/references.bib
docs/_build/.buildinfo
docs/_build/genindex.html
docs/_build/index.html
docs/_build/objects.inv
docs/_build/py-modindex.html
docs/_build/search.html
docs/_build/searchindex.js
docs/_build/.doctrees/environment.pickle
docs/_build/.doctrees/index.doctree
docs/_build/.doctrees/api/index.doctree
docs/_build/.doctrees/api/fleras/EasyDict.__setattr__.doctree
docs/_build/.doctrees/api/fleras/EasyDict.__setitem__.doctree
docs/_build/.doctrees/api/fleras/EasyDict.doctree
docs/_build/.doctrees/api/fleras/EasyDict.pop.doctree
docs/_build/.doctrees/api/fleras/EasyDict.update.doctree
docs/_build/.doctrees/api/fleras/TrainingJob.doctree
docs/_build/.doctrees/api/fleras/index.doctree
docs/_build/.doctrees/api/fleras/fused_renorm/BatchNormalization.doctree
docs/_build/.doctrees/api/fleras/fused_renorm/index.doctree
docs/_build/_sources/index.rst.txt
docs/_build/_sources/api/index.rst.txt
docs/_build/_sources/api/fleras/EasyDict.__setattr__.rst.txt
docs/_build/_sources/api/fleras/EasyDict.__setitem__.rst.txt
docs/_build/_sources/api/fleras/EasyDict.pop.rst.txt
docs/_build/_sources/api/fleras/EasyDict.rst.txt
docs/_build/_sources/api/fleras/EasyDict.update.rst.txt
docs/_build/_sources/api/fleras/TrainingJob.rst.txt
docs/_build/_sources/api/fleras/index.rst.txt
docs/_build/_sources/api/fleras/fused_renorm/BatchNormalization.rst.txt
docs/_build/_sources/api/fleras/fused_renorm/index.rst.txt
docs/_build/_static/basic.css
docs/_build/_static/doctools.js
docs/_build/_static/documentation_options.js
docs/_build/_static/file.png
docs/_build/_static/graphviz.css
docs/_build/_static/language_data.js
docs/_build/_static/minus.png
docs/_build/_static/plus.png
docs/_build/_static/pygments.css
docs/_build/_static/searchtools.js
docs/_build/_static/sphinx_highlight.js
src/florch.egg-info/PKG-INFO
src/florch.egg-info/SOURCES.txt
src/florch.egg-info/dependency_links.txt
src/florch.egg-info/requires.txt
src/florch.egg-info/top_level.txt
